[
  {
    "rank": 1,
    "artist": "Lady Gaga",
    "title": "Poker Face",
    "detailUrl": "https://www.offiziellecharts.de/charts/titel-details-500112"
  },
  {
    "rank": 2,
    "artist": "Emilíana Torrini",
    "title": "Jungle Drum",
    "detailUrl": "https://www.offiziellecharts.de/charts/titel-details-509737"
  },
  {
    "rank": 3,
    "artist": "Milow",
    "title": "Ayo Technology",
    "detailUrl": "https://www.offiziellecharts.de/charts/titel-details-480348"
  },
  {
    "rank": 4,
    "artist": "Cassandra Steen feat. Adel Tawil",
    "title": "Stadt",
    "detailUrl": "https://www.offiziellecharts.de/charts/titel-details-571371"
  },
  {
    "rank": 5,
    "artist": "Mando Diao",
    "title": "Dance With Somebody",
    "detailUrl": "https://www.offiziellecharts.de/charts/titel-details-536832"
  },
  {
    "rank": 6,
    "artist": "Razorlight",
    "title": "Wire To Wire",
    "detailUrl": "https://www.offiziellecharts.de/charts/titel-details-512326"
  },
  {
    "rank": 7,
    "artist": "Silbermond",
    "title": "Irgendwas bleibt",
    "detailUrl": "https://www.offiziellecharts.de/charts/titel-details-549043"
  },
  {
    "rank": 8,
    "artist": "Gossip",
    "title": "Heavy Cross",
    "detailUrl": "https://www.offiziellecharts.de/charts/titel-details-577299"
  },
  {
    "rank": 9,
    "artist": "The Black Eyed Peas",
    "title": "I Gotta Feeling",
    "detailUrl": "https://www.offiziellecharts.de/charts/titel-details-584715"
  },
  {
    "rank": 10,
    "artist": "David Guetta feat. Kelly Rowland",
    "title": "When Love Takes Over",
    "detailUrl": "https://www.offiziellecharts.de/charts/titel-details-576092"
  },
  {
    "rank": 11,
    "artist": "Marit Larsen",
    "title": "If A Song Could Get Me You",
    "detailUrl": "https://www.offiziellecharts.de/charts/titel-details-503517"
  },
  {
    "rank": 12,
    "artist": "James Morrison feat. Nelly Furtado",
    "title": "Broken Strings",
    "detailUrl": "https://www.offiziellecharts.de/charts/titel-details-517552"
  },
  {
    "rank": 13,
    "artist": "Katy Perry",
    "title": "Hot N Cold",
    "detailUrl": "https://www.offiziellecharts.de/charts/titel-details-464160"
  },
  {
    "rank": 14,
    "artist": "David Guetta feat. Akon",
    "title": "Sexy Bitch",
    "detailUrl": "https://www.offiziellecharts.de/charts/titel-details-600196"
  },
  {
    "rank": 15,
    "artist": "Polarkreis 18",
    "title": "Allein allein",
    "detailUrl": "https://www.offiziellecharts.de/charts/titel-details-512982"
  },
  {
    "rank": 16,
    "artist": "Robbie Williams",
    "title": "Bodies",
    "detailUrl": "https://www.offiziellecharts.de/charts/titel-details-611930"
  },
  {
    "rank": 17,
    "artist": "Peter Fox",
    "title": "Haus am See",
    "detailUrl": "https://www.offiziellecharts.de/charts/titel-details-515524"
  },
  {
    "rank": 18,
    "artist": "Beyoncé",
    "title": "Halo",
    "detailUrl": "https://www.offiziellecharts.de/charts/titel-details-529467"
  },
  {
    "rank": 19,
    "artist": "Daniel Schuhmacher",
    "title": "Anything But Love",
    "detailUrl": "https://www.offiziellecharts.de/charts/titel-details-580994"
  },
  {
    "rank": 20,
    "artist": "Mark Medlock",
    "title": "Mamacita",
    "detailUrl": "https://www.offiziellecharts.de/charts/titel-details-568003"
  },
  {
    "rank": 21,
    "artist": "Flo Rida feat. Ke$ha",
    "title": "Right Round",
    "detailUrl": "https://www.offiziellecharts.de/charts/titel-details-551828"
  },
  {
    "rank": 22,
    "artist": "The Killers",
    "title": "Human",
    "detailUrl": "https://www.offiziellecharts.de/charts/titel-details-514714"
  },
  {
    "rank": 23,
    "artist": "Frauenarzt & Manny Marc",
    "title": "Das geht ab! (Wir feiern die ganze Nacht)",
    "detailUrl": "https://www.offiziellecharts.de/charts/titel-details-574251"
  },
  {
    "rank": 24,
    "artist": "Lady Gaga",
    "title": "Paparazzi",
    "detailUrl": "https://www.offiziellecharts.de/charts/titel-details-499538"
  },
  {
    "rank": 25,
    "artist": "Cascada",
    "title": "Evacuate The Dancefloor",
    "detailUrl": "https://www.offiziellecharts.de/charts/titel-details-582968"
  },
  {
    "rank": 26,
    "artist": "Sportfreunde Stiller",
    "title": "Ein Kompliment",
    "detailUrl": "https://www.offiziellecharts.de/charts/titel-details-17860"
  },
  {
    "rank": 27,
    "artist": "The Black Eyed Peas",
    "title": "Boom Boom Pow",
    "detailUrl": "https://www.offiziellecharts.de/charts/titel-details-559837"
  },
  {
    "rank": 28,
    "artist": "Ich + Ich",
    "title": "Pflaster",
    "detailUrl": "https://www.offiziellecharts.de/charts/titel-details-624628"
  },
  {
    "rank": 29,
    "artist": "Amy Macdonald",
    "title": "This Is The Life",
    "detailUrl": "https://www.offiziellecharts.de/charts/titel-details-349688"
  },
  {
    "rank": 30,
    "artist": "P!nk",
    "title": "Sober",
    "detailUrl": "https://www.offiziellecharts.de/charts/titel-details-522741"
  },
  {
    "rank": 31,
    "artist": "Guru Josh Project",
    "title": "Infinity 2008",
    "detailUrl": "https://www.offiziellecharts.de/charts/titel-details-484499"
  },
  {
    "rank": 32,
    "artist": "Kelly Clarkson",
    "title": "My Life Would Suck Without You",
    "detailUrl": "https://www.offiziellecharts.de/charts/titel-details-549386"
  },
  {
    "rank": 33,
    "artist": "Linkin Park",
    "title": "New Divide",
    "detailUrl": "https://www.offiziellecharts.de/charts/titel-details-582297"
  },
  {
    "rank": 34,
    "artist": "Lady Gaga feat. Colby O'Donis",
    "title": "Just Dance",
    "detailUrl": "https://www.offiziellecharts.de/charts/titel-details-481954"
  },
  {
    "rank": 35,
    "artist": "Lily Allen",
    "title": "Not Fair",
    "detailUrl": "https://www.offiziellecharts.de/charts/titel-details-555222"
  },
  {
    "rank": 36,
    "artist": "Nelly Furtado",
    "title": "Manos al aire",
    "detailUrl": "https://www.offiziellecharts.de/charts/titel-details-594659"
  },
  {
    "rank": 37,
    "artist": "Agnes",
    "title": "Release Me",
    "detailUrl": "https://www.offiziellecharts.de/charts/titel-details-540704"
  },
  {
    "rank": 38,
    "artist": "Pitbull",
    "title": "I Know You Want Me (Calle Ocho)",
    "detailUrl": "https://www.offiziellecharts.de/charts/titel-details-565146"
  },
  {
    "rank": 39,
    "artist": "Shakira",
    "title": "She Wolf",
    "detailUrl": "https://www.offiziellecharts.de/charts/titel-details-594866"
  },
  {
    "rank": 40,
    "artist": "Beyoncé",
    "title": "Sweet Dreams",
    "detailUrl": "https://www.offiziellecharts.de/charts/titel-details-530916"
  },
  {
    "rank": 41,
    "artist": "a-ha",
    "title": "Foot Of The Mountain",
    "detailUrl": "https://www.offiziellecharts.de/charts/titel-details-577309"
  },
  {
    "rank": 42,
    "artist": "Metro Station",
    "title": "Shake It",
    "detailUrl": "https://www.offiziellecharts.de/charts/titel-details-462773"
  },
  {
    "rank": 43,
    "artist": "Rammstein",
    "title": "Pussy",
    "detailUrl": "https://www.offiziellecharts.de/charts/titel-details-618698"
  },
  {
    "rank": 44,
    "artist": "Eisblume",
    "title": "Eisblumen",
    "detailUrl": "https://www.offiziellecharts.de/charts/titel-details-548928"
  },
  {
    "rank": 45,
    "artist": "Depeche Mode",
    "title": "Wrong",
    "detailUrl": "https://www.offiziellecharts.de/charts/titel-details-557196"
  },
  {
    "rank": 46,
    "artist": "Beyoncé",
    "title": "If I Were A Boy",
    "detailUrl": "https://www.offiziellecharts.de/charts/titel-details-511766"
  },
  {
    "rank": 47,
    "artist": "Alexander Rybak",
    "title": "Fairytale",
    "detailUrl": "https://www.offiziellecharts.de/charts/titel-details-557605"
  },
  {
    "rank": 48,
    "artist": "Madonna",
    "title": "Celebration",
    "detailUrl": "https://www.offiziellecharts.de/charts/titel-details-598573"
  },
  {
    "rank": 49,
    "artist": "Milow",
    "title": "You Don't Know",
    "detailUrl": "https://www.offiziellecharts.de/charts/titel-details-298277"
  },
  {
    "rank": 50,
    "artist": "Queensberry",
    "title": "Too Young",
    "detailUrl": "https://www.offiziellecharts.de/charts/titel-details-576174"
  },
  {
    "rank": 51,
    "artist": "Tim Toupet",
    "title": "...so ein schöner Tag (Fliegerlied)",
    "detailUrl": "https://www.offiziellecharts.de/charts/titel-details-548881"
  },
  {
    "rank": 52,
    "artist": "Clueso",
    "title": "Gewinner",
    "detailUrl": "https://www.offiziellecharts.de/charts/titel-details-470326"
  },
  {
    "rank": 53,
    "artist": "P!nk",
    "title": "Please Don't Leave Me",
    "detailUrl": "https://www.offiziellecharts.de/charts/titel-details-523080"
  },
  {
    "rank": 54,
    "artist": "Jan Delay",
    "title": "Oh Jonny",
    "detailUrl": "https://www.offiziellecharts.de/charts/titel-details-596878"
  },
  {
    "rank": 55,
    "artist": "Xavier Naidoo",
    "title": "Alles kann besser werden",
    "detailUrl": "https://www.offiziellecharts.de/charts/titel-details-629901"
  },
  {
    "rank": 56,
    "artist": "Curse mit Silbermond",
    "title": "Bis zum Schluss",
    "detailUrl": "https://www.offiziellecharts.de/charts/titel-details-516023"
  },
  {
    "rank": 57,
    "artist": "Rihanna",
    "title": "Rehab",
    "detailUrl": "https://www.offiziellecharts.de/charts/titel-details-320343"
  },
  {
    "rank": 58,
    "artist": "Kings Of Leon",
    "title": "Use Somebody",
    "detailUrl": "https://www.offiziellecharts.de/charts/titel-details-513669"
  },
  {
    "rank": 59,
    "artist": "Peter Fox",
    "title": "Schwarz zu blau",
    "detailUrl": "https://www.offiziellecharts.de/charts/titel-details-515523"
  },
  {
    "rank": 60,
    "artist": "OneRepublic",
    "title": "Secrets",
    "detailUrl": "https://www.offiziellecharts.de/charts/titel-details-613525"
  },
  {
    "rank": 61,
    "artist": "La Roux",
    "title": "Bulletproof",
    "detailUrl": "https://www.offiziellecharts.de/charts/titel-details-567904"
  },
  {
    "rank": 62,
    "artist": "Leona Lewis",
    "title": "Run",
    "detailUrl": "https://www.offiziellecharts.de/charts/titel-details-425610"
  },
  {
    "rank": 63,
    "artist": "Laura Pausini & James Blunt",
    "title": "Primavera in anticipo (It Is My Song)",
    "detailUrl": "https://www.offiziellecharts.de/charts/titel-details-532088"
  },
  {
    "rank": 64,
    "artist": "Rihanna",
    "title": "Russian Roulette",
    "detailUrl": "https://www.offiziellecharts.de/charts/titel-details-634913"
  },
  {
    "rank": 65,
    "artist": "Charlie Winston",
    "title": "Like A Hobo",
    "detailUrl": "https://www.offiziellecharts.de/charts/titel-details-548818"
  },
  {
    "rank": 66,
    "artist": "The All-American Rejects",
    "title": "Gives You Hell",
    "detailUrl": "https://www.offiziellecharts.de/charts/titel-details-534354"
  },
  {
    "rank": 67,
    "artist": "Kevin Rudolf feat. Lil Wayne",
    "title": "Let It Rock",
    "detailUrl": "https://www.offiziellecharts.de/charts/titel-details-506144"
  },
  {
    "rank": 68,
    "artist": "Lady Gaga",
    "title": "LoveGame",
    "detailUrl": "https://www.offiziellecharts.de/charts/titel-details-494228"
  },
  {
    "rank": 69,
    "artist": "The Black Eyed Peas",
    "title": "Meet Me Halfway",
    "detailUrl": "https://www.offiziellecharts.de/charts/titel-details-588992"
  },
  {
    "rank": 70,
    "artist": "Aura Dione",
    "title": "I Will Love You Monday (365)",
    "detailUrl": "https://www.offiziellecharts.de/charts/titel-details-647594"
  },
  {
    "rank": 71,
    "artist": "Kid Cudi vs. Crookers",
    "title": "Day 'N' Nite",
    "detailUrl": "https://www.offiziellecharts.de/charts/titel-details-527743"
  },
  {
    "rank": 72,
    "artist": "Green Day",
    "title": "21 Guns",
    "detailUrl": "https://www.offiziellecharts.de/charts/titel-details-582075"
  },
  {
    "rank": 73,
    "artist": "Culcha Candela",
    "title": "Monsta",
    "detailUrl": "https://www.offiziellecharts.de/charts/titel-details-615802"
  },
  {
    "rank": 74,
    "artist": "Silbermond",
    "title": "Krieger des Lichts",
    "detailUrl": "https://www.offiziellecharts.de/charts/titel-details-558907"
  },
  {
    "rank": 75,
    "artist": "Maria Mena",
    "title": "All This Time (Pick-Me-Up Song)",
    "detailUrl": "https://www.offiziellecharts.de/charts/titel-details-507778"
  },
  {
    "rank": 76,
    "artist": "Culcha Candela",
    "title": "Schöne neue Welt",
    "detailUrl": "https://www.offiziellecharts.de/charts/titel-details-602925"
  },
  {
    "rank": 77,
    "artist": "P!nk",
    "title": "So What",
    "detailUrl": "https://www.offiziellecharts.de/charts/titel-details-498944"
  },
  {
    "rank": 78,
    "artist": "Pet Shop Boys",
    "title": "Love etc.",
    "detailUrl": "https://www.offiziellecharts.de/charts/titel-details-554484"
  },
  {
    "rank": 79,
    "artist": "Lily Allen",
    "title": "The Fear",
    "detailUrl": "https://www.offiziellecharts.de/charts/titel-details-454108"
  },
  {
    "rank": 80,
    "artist": "T.I. feat. Justin Timberlake",
    "title": "Dead And Gone",
    "detailUrl": "https://www.offiziellecharts.de/charts/titel-details-529513"
  },
  {
    "rank": 81,
    "artist": "Bushido feat. Karel Gott",
    "title": "Für immer jung",
    "detailUrl": "https://www.offiziellecharts.de/charts/titel-details-520718"
  },
  {
    "rank": 82,
    "artist": "P!nk",
    "title": "Funhouse",
    "detailUrl": "https://www.offiziellecharts.de/charts/titel-details-523036"
  },
  {
    "rank": 83,
    "artist": "The Pussycat Dolls",
    "title": "I Hate This Part",
    "detailUrl": "https://www.offiziellecharts.de/charts/titel-details-513752"
  },
  {
    "rank": 84,
    "artist": "Sido",
    "title": "Hey du",
    "detailUrl": "https://www.offiziellecharts.de/charts/titel-details-626989"
  },
  {
    "rank": 85,
    "artist": "Bon Jovi",
    "title": "We Weren't Born To Follow",
    "detailUrl": "https://www.offiziellecharts.de/charts/titel-details-613449"
  },
  {
    "rank": 86,
    "artist": "Kings Of Leon",
    "title": "Sex On Fire",
    "detailUrl": "https://www.offiziellecharts.de/charts/titel-details-498651"
  },
  {
    "rank": 87,
    "artist": "Coldplay",
    "title": "Viva la vida",
    "detailUrl": "https://www.offiziellecharts.de/charts/titel-details-464829"
  },
  {
    "rank": 88,
    "artist": "Queensberry",
    "title": "Hello (Turn Your Radio On)",
    "detailUrl": "https://www.offiziellecharts.de/charts/titel-details-624731"
  },
  {
    "rank": 89,
    "artist": "Söhne Mannheims",
    "title": "Ich wollt nur deine Stimme hörn",
    "detailUrl": "https://www.offiziellecharts.de/charts/titel-details-601836"
  },
  {
    "rank": 90,
    "artist": "DJ Ötzi",
    "title": "Noch in 100.000 Jahren",
    "detailUrl": "https://www.offiziellecharts.de/charts/titel-details-492879"
  },
  {
    "rank": 91,
    "artist": "Leona Lewis",
    "title": "Happy",
    "detailUrl": "https://www.offiziellecharts.de/charts/titel-details-618694"
  },
  {
    "rank": 92,
    "artist": "Daniel Merriweather feat. Wale",
    "title": "Change",
    "detailUrl": "https://www.offiziellecharts.de/charts/titel-details-556322"
  },
  {
    "rank": 93,
    "artist": "Cassandra Steen",
    "title": "Darum leben wir",
    "detailUrl": "https://www.offiziellecharts.de/charts/titel-details-550593"
  },
  {
    "rank": 94,
    "artist": "T.I. feat. Rihanna",
    "title": "Live Your Life",
    "detailUrl": "https://www.offiziellecharts.de/charts/titel-details-510122"
  },
  {
    "rank": 95,
    "artist": "Katy Perry",
    "title": "I Kissed A Girl",
    "detailUrl": "https://www.offiziellecharts.de/charts/titel-details-464153"
  },
  {
    "rank": 96,
    "artist": "Reamonn",
    "title": "Moments Like This",
    "detailUrl": "https://www.offiziellecharts.de/charts/titel-details-528844"
  },
  {
    "rank": 97,
    "artist": "Enrique Iglesias feat. Sarah Connor",
    "title": "Takin' Back My Love",
    "detailUrl": "https://www.offiziellecharts.de/charts/titel-details-550424"
  },
  {
    "rank": 98,
    "artist": "The Last Goodnight",
    "title": "Pictures Of You",
    "detailUrl": "https://www.offiziellecharts.de/charts/titel-details-331629"
  },
  {
    "rank": 99,
    "artist": "Herbert Grönemeyer",
    "title": "Glück",
    "detailUrl": "https://www.offiziellecharts.de/charts/titel-details-528379"
  },
  {
    "rank": 100,
    "artist": "Britney Spears",
    "title": "Womanizer",
    "detailUrl": "https://www.offiziellecharts.de/charts/titel-details-513208"
  }
]