[
  {
    "rank": 1,
    "artist": "OMD (Orchestral Manoeuvres In The Dark)",
    "title": "Maid Of Orleans (The Waltz Joan Of Arc)",
    "detailUrl": "https://www.offiziellecharts.de/charts/titel-details-843"
  },
  {
    "rank": 2,
    "artist": "Spider Murphy Gang",
    "title": "Skandal im Sperrbezirk",
    "detailUrl": "https://www.offiziellecharts.de/charts/titel-details-817"
  },
  {
    "rank": 3,
    "artist": "Al Bano & Romina Power",
    "title": "Felicità",
    "detailUrl": "https://www.offiziellecharts.de/charts/titel-details-815"
  },
  {
    "rank": 4,
    "artist": "Andy Borg",
    "title": "Adios amor",
    "detailUrl": "https://www.offiziellecharts.de/charts/titel-details-869"
  },
  {
    "rank": 5,
    "artist": "Falco",
    "title": "Der Kommissar",
    "detailUrl": "https://www.offiziellecharts.de/charts/titel-details-809"
  },
  {
    "rank": 6,
    "artist": "Trio",
    "title": "Da da da ich lieb dich nicht du liebst mich nicht aha aha aha",
    "detailUrl": "https://www.offiziellecharts.de/charts/titel-details-842"
  },
  {
    "rank": 7,
    "artist": "Joachim Witt",
    "title": "Goldener Reiter",
    "detailUrl": "https://www.offiziellecharts.de/charts/titel-details-7323"
  },
  {
    "rank": 8,
    "artist": "Nicole",
    "title": "Ein bißchen Frieden",
    "detailUrl": "https://www.offiziellecharts.de/charts/titel-details-833"
  },
  {
    "rank": 9,
    "artist": "Alice",
    "title": "Una notte speciale",
    "detailUrl": "https://www.offiziellecharts.de/charts/titel-details-26936"
  },
  {
    "rank": 10,
    "artist": "Markus",
    "title": "Ich will Spaß",
    "detailUrl": "https://www.offiziellecharts.de/charts/titel-details-7319"
  },
  {
    "rank": 11,
    "artist": "Al Bano & Romina Power",
    "title": "Sharazan",
    "detailUrl": "https://www.offiziellecharts.de/charts/titel-details-795"
  },
  {
    "rank": 12,
    "artist": "Hubert Kah",
    "title": "Rosemarie",
    "detailUrl": "https://www.offiziellecharts.de/charts/titel-details-848"
  },
  {
    "rank": 13,
    "artist": "Imagination",
    "title": "Just An Illusion",
    "detailUrl": "https://www.offiziellecharts.de/charts/titel-details-847"
  },
  {
    "rank": 14,
    "artist": "Paul McCartney & Stevie Wonder",
    "title": "Ebony And Ivory",
    "detailUrl": "https://www.offiziellecharts.de/charts/titel-details-834"
  },
  {
    "rank": 15,
    "artist": "Kim Wilde",
    "title": "Cambodia",
    "detailUrl": "https://www.offiziellecharts.de/charts/titel-details-798"
  },
  {
    "rank": 16,
    "artist": "Grauzone",
    "title": "Eisbär",
    "detailUrl": "https://www.offiziellecharts.de/charts/titel-details-6914"
  },
  {
    "rank": 17,
    "artist": "Spliff",
    "title": "Carbonara",
    "detailUrl": "https://www.offiziellecharts.de/charts/titel-details-853"
  },
  {
    "rank": 18,
    "artist": "Men At Work",
    "title": "Down Under",
    "detailUrl": "https://www.offiziellecharts.de/charts/titel-details-851"
  },
  {
    "rank": 19,
    "artist": "Christian Franke",
    "title": "Ich wünsch' dir die Hölle auf Erden (wenn du heut' gehst)",
    "detailUrl": "https://www.offiziellecharts.de/charts/titel-details-15353"
  },
  {
    "rank": 20,
    "artist": "Gottlieb Wendehals",
    "title": "Polonäse Blankenese",
    "detailUrl": "https://www.offiziellecharts.de/charts/titel-details-813"
  },
  {
    "rank": 21,
    "artist": "Ricchi & Poveri",
    "title": "Made In Italy",
    "detailUrl": "https://www.offiziellecharts.de/charts/titel-details-870"
  },
  {
    "rank": 22,
    "artist": "Karat",
    "title": "Der blaue Planet",
    "detailUrl": "https://www.offiziellecharts.de/charts/titel-details-13630"
  },
  {
    "rank": 23,
    "artist": "Shakin' Stevens",
    "title": "Oh Julie",
    "detailUrl": "https://www.offiziellecharts.de/charts/titel-details-808"
  },
  {
    "rank": 24,
    "artist": "Spider Murphy Gang",
    "title": "Schickeria",
    "detailUrl": "https://www.offiziellecharts.de/charts/titel-details-837"
  },
  {
    "rank": 25,
    "artist": "ABBA",
    "title": "One Of Us",
    "detailUrl": "https://www.offiziellecharts.de/charts/titel-details-797"
  },
  {
    "rank": 26,
    "artist": "Spider Murphy Gang",
    "title": "Wo bist du?",
    "detailUrl": "https://www.offiziellecharts.de/charts/titel-details-864"
  },
  {
    "rank": 27,
    "artist": "Claudia Mori",
    "title": "Non succederà più",
    "detailUrl": "https://www.offiziellecharts.de/charts/titel-details-828"
  },
  {
    "rank": 28,
    "artist": "Ph.D.",
    "title": "I Won't Let You Down",
    "detailUrl": "https://www.offiziellecharts.de/charts/titel-details-823"
  },
  {
    "rank": 29,
    "artist": "Dave Stewart with Barbara Gaskin",
    "title": "It's My Party",
    "detailUrl": "https://www.offiziellecharts.de/charts/titel-details-801"
  },
  {
    "rank": 30,
    "artist": "Jon And Vangelis",
    "title": "I'll Find My Way Home",
    "detailUrl": "https://www.offiziellecharts.de/charts/titel-details-818"
  },
  {
    "rank": 31,
    "artist": "Extrabreit",
    "title": "Hurra, hurra, die Schule brennt",
    "detailUrl": "https://www.offiziellecharts.de/charts/titel-details-88563"
  },
  {
    "rank": 32,
    "artist": "Steve Miller Band",
    "title": "Abracadabra",
    "detailUrl": "https://www.offiziellecharts.de/charts/titel-details-862"
  },
  {
    "rank": 33,
    "artist": "UKW",
    "title": "Sommersprossen",
    "detailUrl": "https://www.offiziellecharts.de/charts/titel-details-849"
  },
  {
    "rank": 34,
    "artist": "Joan Jett & The Blackhearts",
    "title": "I Love Rock'n Roll",
    "detailUrl": "https://www.offiziellecharts.de/charts/titel-details-826"
  },
  {
    "rank": 35,
    "artist": "Soft Cell",
    "title": "Tainted Love",
    "detailUrl": "https://www.offiziellecharts.de/charts/titel-details-792"
  },
  {
    "rank": 36,
    "artist": "Peter Cornelius",
    "title": "Du entschuldige - i kenn' di",
    "detailUrl": "https://www.offiziellecharts.de/charts/titel-details-802"
  },
  {
    "rank": 37,
    "artist": "Roger Whittaker",
    "title": "Albany",
    "detailUrl": "https://www.offiziellecharts.de/charts/titel-details-832"
  },
  {
    "rank": 38,
    "artist": "ZaZa",
    "title": "Zauberstab",
    "detailUrl": "https://www.offiziellecharts.de/charts/titel-details-7337"
  },
  {
    "rank": 39,
    "artist": "Hot Chocolate",
    "title": "Girl Crazy",
    "detailUrl": "https://www.offiziellecharts.de/charts/titel-details-24057"
  },
  {
    "rank": 40,
    "artist": "The J. Geils Band",
    "title": "Centerfold",
    "detailUrl": "https://www.offiziellecharts.de/charts/titel-details-822"
  },
  {
    "rank": 41,
    "artist": "Ricky King",
    "title": "Halé, Hey Louise",
    "detailUrl": "https://www.offiziellecharts.de/charts/titel-details-15347"
  },
  {
    "rank": 42,
    "artist": "James Last",
    "title": "Biscaya",
    "detailUrl": "https://www.offiziellecharts.de/charts/titel-details-37564"
  },
  {
    "rank": 43,
    "artist": "Kraftwerk",
    "title": "Das Model",
    "detailUrl": "https://www.offiziellecharts.de/charts/titel-details-10698"
  },
  {
    "rank": 44,
    "artist": "Bucks Fizz",
    "title": "The Land Of Make Believe",
    "detailUrl": "https://www.offiziellecharts.de/charts/titel-details-9257"
  },
  {
    "rank": 45,
    "artist": "Rheingold",
    "title": "Dreiklangs-Dimensionen",
    "detailUrl": "https://www.offiziellecharts.de/charts/titel-details-7357"
  },
  {
    "rank": 46,
    "artist": "Tight Fit",
    "title": "The Lion Sleeps Tonight",
    "detailUrl": "https://www.offiziellecharts.de/charts/titel-details-831"
  },
  {
    "rank": 47,
    "artist": "F-R David",
    "title": "Words",
    "detailUrl": "https://www.offiziellecharts.de/charts/titel-details-874"
  },
  {
    "rank": 48,
    "artist": "David Christie",
    "title": "Saddle Up",
    "detailUrl": "https://www.offiziellecharts.de/charts/titel-details-871"
  },
  {
    "rank": 49,
    "artist": "Barrabas",
    "title": "On The Road Again",
    "detailUrl": "https://www.offiziellecharts.de/charts/titel-details-821"
  },
  {
    "rank": 50,
    "artist": "Adam Ant",
    "title": "Goody Two Shoes",
    "detailUrl": "https://www.offiziellecharts.de/charts/titel-details-9120"
  },
  {
    "rank": 51,
    "artist": "Kim Wilde",
    "title": "View From A Bridge",
    "detailUrl": "https://www.offiziellecharts.de/charts/titel-details-835"
  },
  {
    "rank": 52,
    "artist": "Peter Maffay",
    "title": "Lieber Gott...",
    "detailUrl": "https://www.offiziellecharts.de/charts/titel-details-811"
  },
  {
    "rank": 53,
    "artist": "Yazoo",
    "title": "Don't Go",
    "detailUrl": "https://www.offiziellecharts.de/charts/titel-details-880"
  },
  {
    "rank": 54,
    "artist": "The Human League",
    "title": "Don't You Want Me",
    "detailUrl": "https://www.offiziellecharts.de/charts/titel-details-824"
  },
  {
    "rank": 55,
    "artist": "Asia",
    "title": "Heat Of The Moment",
    "detailUrl": "https://www.offiziellecharts.de/charts/titel-details-860"
  },
  {
    "rank": 56,
    "artist": "BAP",
    "title": "Verdamp lang her",
    "detailUrl": "https://www.offiziellecharts.de/charts/titel-details-9243"
  },
  {
    "rank": 57,
    "artist": "Helen Schneider",
    "title": "Rock'n'Roll Gypsy",
    "detailUrl": "https://www.offiziellecharts.de/charts/titel-details-806"
  },
  {
    "rank": 58,
    "artist": "Karat",
    "title": "Jede Stunde",
    "detailUrl": "https://www.offiziellecharts.de/charts/titel-details-20865"
  },
  {
    "rank": 59,
    "artist": "Jawoll",
    "title": "Taxi",
    "detailUrl": "https://www.offiziellecharts.de/charts/titel-details-15464"
  },
  {
    "rank": 60,
    "artist": "Rolf und seine Freunde",
    "title": "... und ganz doll mich (ich mag)",
    "detailUrl": "https://www.offiziellecharts.de/charts/titel-details-54881"
  },
  {
    "rank": 61,
    "artist": "Olivia Newton-John",
    "title": "Physical",
    "detailUrl": "https://www.offiziellecharts.de/charts/titel-details-783"
  },
  {
    "rank": 62,
    "artist": "Frank Zander",
    "title": "Da da da ich weiß Bescheid, du weißt Bescheid",
    "detailUrl": "https://www.offiziellecharts.de/charts/titel-details-857"
  },
  {
    "rank": 63,
    "artist": "Aneka",
    "title": "Little Lady",
    "detailUrl": "https://www.offiziellecharts.de/charts/titel-details-14886"
  },
  {
    "rank": 64,
    "artist": "Ideal",
    "title": "Eiszeit",
    "detailUrl": "https://www.offiziellecharts.de/charts/titel-details-18747"
  },
  {
    "rank": 65,
    "artist": "Peter Alexander",
    "title": "Der Papa wird's schon richten",
    "detailUrl": "https://www.offiziellecharts.de/charts/titel-details-11996"
  },
  {
    "rank": 66,
    "artist": "Chicago",
    "title": "Hard To Say I'm Sorry",
    "detailUrl": "https://www.offiziellecharts.de/charts/titel-details-866"
  },
  {
    "rank": 67,
    "artist": "Udo Lindenberg & Pascal",
    "title": "Wozu sind Kriege da?",
    "detailUrl": "https://www.offiziellecharts.de/charts/titel-details-25457"
  },
  {
    "rank": 68,
    "artist": "Shakin' Stevens",
    "title": "Shirley",
    "detailUrl": "https://www.offiziellecharts.de/charts/titel-details-838"
  },
  {
    "rank": 69,
    "artist": "Fred Sonnenschein und seine Freunde",
    "title": "Ja, wenn wir alle Englein wären",
    "detailUrl": "https://www.offiziellecharts.de/charts/titel-details-789"
  },
  {
    "rank": 70,
    "artist": "Falco",
    "title": "Maschine brennt",
    "detailUrl": "https://www.offiziellecharts.de/charts/titel-details-18744"
  },
  {
    "rank": 71,
    "artist": "Nena",
    "title": "Nur geträumt",
    "detailUrl": "https://www.offiziellecharts.de/charts/titel-details-893"
  },
  {
    "rank": 72,
    "artist": "Relax",
    "title": "Weil i di mog",
    "detailUrl": "https://www.offiziellecharts.de/charts/titel-details-883"
  },
  {
    "rank": 73,
    "artist": "Frl. Menke",
    "title": "Hohe Berge",
    "detailUrl": "https://www.offiziellecharts.de/charts/titel-details-7339"
  },
  {
    "rank": 74,
    "artist": "Foreigner",
    "title": "Urgent",
    "detailUrl": "https://www.offiziellecharts.de/charts/titel-details-6546"
  },
  {
    "rank": 75,
    "artist": "Frida",
    "title": "I Know There's Something Going On",
    "detailUrl": "https://www.offiziellecharts.de/charts/titel-details-873"
  }
]