[
  {
    "rank": 1,
    "artist": "David Hasselhoff",
    "title": "Looking For Freedom",
    "deezer": {
      "deezerID": 122469884,
      "deezerLink": "https://www.deezer.com/track/122469884",
      "cover": "https://cdn-images.dzcdn.net/images/cover/d8bc7032d3407e43b8cf4c4578ab12c0/500x500-000000-80-0-0.jpg",
      "deezerArtist": "David Hasselhoff",
      "deezerTitle": "Looking for Freedom"
    }
  },
  {
    "rank": 2,
    "artist": "Mysterious Art",
    "title": "Das Omen (Teil 1)"
  },
  {
    "rank": 3,
    "artist": "Robin Beck",
    "title": "First Time",
    "deezer": {
      "deezerID": 907667,
      "deezerLink": "https://www.deezer.com/track/907667",
      "cover": "https://cdn-images.dzcdn.net/images/cover/6fb2093c2602a72c39100fe36ec4415b/500x500-000000-80-0-0.jpg",
      "deezerArtist": "Robin Beck",
      "deezerTitle": "First Time"
    }
  },
  {
    "rank": 4,
    "artist": "Roxette",
    "title": "The Look",
    "deezer": {
      "deezerID": 3092167,
      "deezerLink": "https://www.deezer.com/track/3092167",
      "cover": "https://cdn-images.dzcdn.net/images/cover/795b45e8a76e80ef4c342b00f9d37845/500x500-000000-80-0-0.jpg",
      "deezerArtist": "Roxette",
      "deezerTitle": "The Look"
    }
  },
  {
    "rank": 5,
    "artist": "Kaoma",
    "title": "Lambada",
    "deezer": {
      "deezerID": 309174,
      "deezerLink": "https://www.deezer.com/track/309174",
      "cover": "https://cdn-images.dzcdn.net/images/cover/fd4d708dc127726804135ff1b80b7a73/500x500-000000-80-0-0.jpg",
      "deezerArtist": "Kaoma",
      "deezerTitle": "Lambada"
    }
  },
  {
    "rank": 6,
    "artist": "Madonna",
    "title": "Like A Prayer",
    "deezer": {
      "deezerID": 664507,
      "deezerLink": "https://www.deezer.com/track/664507",
      "cover": "https://cdn-images.dzcdn.net/images/cover/2abcc790ccb86e8f8615b3f7ea305ee5/500x500-000000-80-0-0.jpg",
      "deezerArtist": "Madonna",
      "deezerTitle": "Like a Prayer"
    }
  },
  {
    "rank": 7,
    "artist": "Jive Bunny And The Mastermixers",
    "title": "Swing The Mood",
    "deezer": {
      "deezerID": 61350123,
      "deezerLink": "https://www.deezer.com/track/61350123",
      "cover": "https://cdn-images.dzcdn.net/images/cover/c9dc71c1275ce2da953cff7e15245ef7/500x500-000000-80-0-0.jpg",
      "deezerArtist": "Jive Bunny And The Mastermixers",
      "deezerTitle": "Swing the Mood"
    }
  },
  {
    "rank": 8,
    "artist": "Fine Young Cannibals",
    "title": "She Drives Me Crazy",
    "deezer": {
      "deezerID": 1178372072,
      "deezerLink": "https://www.deezer.com/track/1178372072",
      "cover": "https://cdn-images.dzcdn.net/images/cover/68887afcc67c38a1eac40577db338322/500x500-000000-80-0-0.jpg",
      "deezerArtist": "Fine Young Cannibals",
      "deezerTitle": "She Drives Me Crazy"
    }
  },
  {
    "rank": 9,
    "artist": "Soulsister",
    "title": "The Way To Your Heart",
    "deezer": {
      "deezerID": 3265593,
      "deezerLink": "https://www.deezer.com/track/3265593",
      "cover": "https://cdn-images.dzcdn.net/images/cover/2b7204a83454c7a10076e48447755e1f/500x500-000000-80-0-0.jpg",
      "deezerArtist": "Soulsister",
      "deezerTitle": "The Way to Your Heart"
    }
  },
  {
    "rank": 10,
    "artist": "Bobby McFerrin",
    "title": "Don't Worry, Be Happy",
    "deezer": {
      "deezerID": 3127387,
      "deezerLink": "https://www.deezer.com/track/3127387",
      "cover": "https://cdn-images.dzcdn.net/images/cover/121ed33882c127248831b9aacfe5220b/500x500-000000-80-0-0.jpg",
      "deezerArtist": "Bobby McFerrin",
      "deezerTitle": "Don't Worry Be Happy"
    }
  },
  {
    "rank": 11,
    "artist": "Marc Almond feat. Gene Pitney",
    "title": "Something's Gotten Hold Of My Heart",
    "deezer": {
      "deezerID": 3099221,
      "deezerLink": "https://www.deezer.com/track/3099221",
      "cover": "https://cdn-images.dzcdn.net/images/cover/b75522d566940b6e3d9dcfe388682b65/500x500-000000-80-0-0.jpg",
      "deezerArtist": "Marc Almond",
      "deezerTitle": "Something's Gotten Hold of My Heart"
    }
  },
  {
    "rank": 12,
    "artist": "The Cure",
    "title": "Lullaby",
    "deezer": {
      "deezerID": 1143637,
      "deezerLink": "https://www.deezer.com/track/1143637",
      "cover": "https://cdn-images.dzcdn.net/images/cover/21d780d99cbe7eb5e1d8b5d31fce28c8/500x500-000000-80-0-0.jpg",
      "deezerArtist": "The Cure",
      "deezerTitle": "Lullaby"
    }
  },
  {
    "rank": 13,
    "artist": "Holly Johnson",
    "title": "Americanos",
    "deezer": {
      "deezerID": 4275259,
      "deezerLink": "https://www.deezer.com/track/4275259",
      "cover": "https://cdn-images.dzcdn.net/images/cover/6827672c0ca3c851f602191c281f1b10/500x500-000000-80-0-0.jpg",
      "deezerArtist": "Holly Johnson",
      "deezerTitle": "Americanos"
    }
  },
  {
    "rank": 14,
    "artist": "Lil Louis",
    "title": "French Kiss",
    "deezer": {
      "deezerID": 15273623,
      "deezerLink": "https://www.deezer.com/track/15273623",
      "cover": "https://cdn-images.dzcdn.net/images/cover/fb4203e1f2b0a0242bd46c9a2796353f/500x500-000000-80-0-0.jpg",
      "deezerArtist": "Lil' Louis",
      "deezerTitle": "French Kiss"
    }
  },
  {
    "rank": 15,
    "artist": "Bangles",
    "title": "Eternal Flame",
    "deezer": {
      "deezerID": 3037340,
      "deezerLink": "https://www.deezer.com/track/3037340",
      "cover": "https://cdn-images.dzcdn.net/images/cover/160a720272bfeac612989f32ae101c0d/500x500-000000-80-0-0.jpg",
      "deezerArtist": "The Bangles",
      "deezerTitle": "Eternal Flame"
    }
  },
  {
    "rank": 16,
    "artist": "Tanita Tikaram",
    "title": "Twist In My Sobriety",
    "deezer": {
      "deezerID": 2686266,
      "deezerLink": "https://www.deezer.com/track/2686266",
      "cover": "https://cdn-images.dzcdn.net/images/cover/2b30c2448ed77dcb8d5f137e224cb4f9/500x500-000000-80-0-0.jpg",
      "deezerArtist": "Tanita Tikaram",
      "deezerTitle": "Twist in My Sobriety"
    }
  },
  {
    "rank": 17,
    "artist": "Paula Abdul",
    "title": "Straight Up",
    "deezer": {
      "deezerID": 3109328,
      "deezerLink": "https://www.deezer.com/track/3109328",
      "cover": "https://cdn-images.dzcdn.net/images/cover/5c128a8af757d0e739afae68cfe2163c/500x500-000000-80-0-0.jpg",
      "deezerArtist": "Paula Abdul",
      "deezerTitle": "Straight Up"
    }
  },
  {
    "rank": 18,
    "artist": "Camouflage",
    "title": "Love Is A Shield",
    "deezer": {
      "deezerID": 5096565,
      "deezerLink": "https://www.deezer.com/track/5096565",
      "cover": "https://cdn-images.dzcdn.net/images/cover/6ef1a3f2f0791c4c9426de3b2cbb07d1/500x500-000000-80-0-0.jpg",
      "deezerArtist": "Camouflage",
      "deezerTitle": "Love Is A Shield"
    }
  },
  {
    "rank": 19,
    "artist": "Simple Minds",
    "title": "Ballad Of The Streets"
  },
  {
    "rank": 20,
    "artist": "Enya",
    "title": "Orinoco Flow",
    "deezer": {
      "deezerID": 65728152,
      "deezerLink": "https://www.deezer.com/track/65728152",
      "cover": "https://cdn-images.dzcdn.net/images/cover/dbac560cff7f416989e1d4918c8a7c9b/500x500-000000-80-0-0.jpg",
      "deezerArtist": "Enya",
      "deezerTitle": "Orinoco Flow"
    }
  },
  {
    "rank": 21,
    "artist": "Neneh Cherry",
    "title": "Buffalo Stance",
    "deezer": {
      "deezerID": 3324536,
      "deezerLink": "https://www.deezer.com/track/3324536",
      "cover": "https://cdn-images.dzcdn.net/images/cover/bdeb514b534c737aba92a28e0264a8c5/500x500-000000-80-0-0.jpg",
      "deezerArtist": "Neneh Cherry",
      "deezerTitle": "Buffalo Stance"
    }
  },
  {
    "rank": 22,
    "artist": "Edelweiss",
    "title": "Bring Me Edelweiss",
    "deezer": {
      "deezerID": 15318548,
      "deezerLink": "https://www.deezer.com/track/15318548",
      "cover": "https://cdn-images.dzcdn.net/images/cover/7e1020620aab4e71c2e79a30ff62535e/500x500-000000-80-0-0.jpg",
      "deezerArtist": "Edelweiss",
      "deezerTitle": "Bring Me Edelweiss"
    }
  },
  {
    "rank": 23,
    "artist": "Don Johnson",
    "title": "Tell It Like It Is",
    "deezer": {
      "deezerID": 5638887,
      "deezerLink": "https://www.deezer.com/track/5638887",
      "cover": "https://cdn-images.dzcdn.net/images/cover/881b1c49da6458c6373746faa8b70cb0/500x500-000000-80-0-0.jpg",
      "deezerArtist": "Don Johnson",
      "deezerTitle": "Tell It Like It Is"
    }
  },
  {
    "rank": 24,
    "artist": "Technotronic feat. Felly",
    "title": "Pump Up The Jam",
    "deezer": {
      "deezerID": 2961498,
      "deezerLink": "https://www.deezer.com/track/2961498",
      "cover": "https://cdn-images.dzcdn.net/images/cover/8ddb94a0ba17254188a54d18b6173f7f/500x500-000000-80-0-0.jpg",
      "deezerArtist": "Technotronic",
      "deezerTitle": "Pump Up The Jam"
    }
  },
  {
    "rank": 25,
    "artist": "Neneh Cherry",
    "title": "Manchild",
    "deezer": {
      "deezerID": 3324537,
      "deezerLink": "https://www.deezer.com/track/3324537",
      "cover": "https://cdn-images.dzcdn.net/images/cover/bdeb514b534c737aba92a28e0264a8c5/500x500-000000-80-0-0.jpg",
      "deezerArtist": "Neneh Cherry",
      "deezerTitle": "Manchild"
    }
  },
  {
    "rank": 26,
    "artist": "Phil Collins",
    "title": "In The Air Tonight ('88 Remix)",
    "deezer": {
      "deezerID": 134036212,
      "deezerLink": "https://www.deezer.com/track/134036212",
      "cover": "https://cdn-images.dzcdn.net/images/cover/73e6481676a8ab3e93f0f7b79a9cff68/500x500-000000-80-0-0.jpg",
      "deezerArtist": "Phil Collins",
      "deezerTitle": "In the Air Tonight"
    }
  },
  {
    "rank": 27,
    "artist": "Tone Loc",
    "title": "Funky Cold Medina"
  },
  {
    "rank": 28,
    "artist": "Milli Vanilli",
    "title": "Blame It On The Rain",
    "deezer": {
      "deezerID": 2463954425,
      "deezerLink": "https://www.deezer.com/track/2463954425",
      "cover": "https://cdn-images.dzcdn.net/images/cover/93438b5905da18db776bad2b7fa0e630/500x500-000000-80-0-0.jpg",
      "deezerArtist": "Milli Vanilli",
      "deezerTitle": "Blame It on the Rain"
    }
  },
  {
    "rank": 29,
    "artist": "Tony Carey",
    "title": "Room With A View"
  },
  {
    "rank": 30,
    "artist": "Soul II Soul",
    "title": "Back To Life (However Do You Want Me)",
    "deezer": {
      "deezerID": 3125988,
      "deezerLink": "https://www.deezer.com/track/3125988",
      "cover": "https://cdn-images.dzcdn.net/images/cover/43edaf5a15623dff51ad07a617cbdf72/500x500-000000-80-0-0.jpg",
      "deezerArtist": "Soul II Soul",
      "deezerTitle": "Back To Life"
    }
  },
  {
    "rank": 31,
    "artist": "Holly Johnson",
    "title": "Love Train",
    "deezer": {
      "deezerID": 7988171,
      "deezerLink": "https://www.deezer.com/track/7988171",
      "cover": "https://cdn-images.dzcdn.net/images/cover/202a7bf0fc6bf5c369dd72f9c8486be1/500x500-000000-80-0-0.jpg",
      "deezerArtist": "Holly Johnson",
      "deezerTitle": "Love Train"
    }
  },
  {
    "rank": 32,
    "artist": "Madonna",
    "title": "Express Yourself",
    "deezer": {
      "deezerID": 664509,
      "deezerLink": "https://www.deezer.com/track/664509",
      "cover": "https://cdn-images.dzcdn.net/images/cover/2abcc790ccb86e8f8615b3f7ea305ee5/500x500-000000-80-0-0.jpg",
      "deezerArtist": "Madonna",
      "deezerTitle": "Express Yourself"
    }
  },
  {
    "rank": 33,
    "artist": "Milli Vanilli",
    "title": "Girl I'm Gonna Miss You",
    "deezer": {
      "deezerID": 2463954555,
      "deezerLink": "https://www.deezer.com/track/2463954555",
      "cover": "https://cdn-images.dzcdn.net/images/cover/93438b5905da18db776bad2b7fa0e630/500x500-000000-80-0-0.jpg",
      "deezerArtist": "Milli Vanilli",
      "deezerTitle": "Girl I'm Gonna Miss You"
    }
  },
  {
    "rank": 34,
    "artist": "Phil Collins",
    "title": "Two Hearts",
    "deezer": {
      "deezerID": 4290192,
      "deezerLink": "https://www.deezer.com/track/4290192",
      "cover": "https://cdn-images.dzcdn.net/images/cover/ec2d744be32e49de57f59513d0e3d5c1/500x500-000000-80-0-0.jpg",
      "deezerArtist": "Phil Collins",
      "deezerTitle": "Two Hearts"
    }
  },
  {
    "rank": 35,
    "artist": "Sydney Youngblood",
    "title": "If Only I Could",
    "deezer": {
      "deezerID": 3257867,
      "deezerLink": "https://www.deezer.com/track/3257867",
      "cover": "https://cdn-images.dzcdn.net/images/cover/2bbbe8a33700356d99d2794fe7bad048/500x500-000000-80-0-0.jpg",
      "deezerArtist": "Sydney Youngblood",
      "deezerTitle": "If Only I Could"
    }
  },
  {
    "rank": 36,
    "artist": "Inner City",
    "title": "Big Fun",
    "deezer": {
      "deezerID": 3133682,
      "deezerLink": "https://www.deezer.com/track/3133682",
      "cover": "https://cdn-images.dzcdn.net/images/cover/1f99d88dcc3a088d660ecb9a4d8bf766/500x500-000000-80-0-0.jpg",
      "deezerArtist": "Inner City",
      "deezerTitle": "Big Fun"
    }
  },
  {
    "rank": 37,
    "artist": "The Beach Boys",
    "title": "Kokomo",
    "deezer": {
      "deezerID": 3091987,
      "deezerLink": "https://www.deezer.com/track/3091987",
      "cover": "https://cdn-images.dzcdn.net/images/cover/ab113555b056cb808b050dff43a9590a/500x500-000000-80-0-0.jpg",
      "deezerArtist": "The Beach Boys",
      "deezerTitle": "Kokomo"
    }
  },
  {
    "rank": 38,
    "artist": "Inner City",
    "title": "Good Life",
    "deezer": {
      "deezerID": 3133684,
      "deezerLink": "https://www.deezer.com/track/3133684",
      "cover": "https://cdn-images.dzcdn.net/images/cover/1f99d88dcc3a088d660ecb9a4d8bf766/500x500-000000-80-0-0.jpg",
      "deezerArtist": "Inner City",
      "deezerTitle": "Good Life"
    }
  },
  {
    "rank": 39,
    "artist": "Sam Brown",
    "title": "Stop!",
    "deezer": {
      "deezerID": 1173523,
      "deezerLink": "https://www.deezer.com/track/1173523",
      "cover": "https://cdn-images.dzcdn.net/images/cover/060a561509b19a06542e3042fd7761ff/500x500-000000-80-0-0.jpg",
      "deezerArtist": "Sam Brown",
      "deezerTitle": "Stop"
    }
  },
  {
    "rank": 40,
    "artist": "Jason Donovan",
    "title": "Sealed With A Kiss",
    "deezer": {
      "deezerID": 137198604,
      "deezerLink": "https://www.deezer.com/track/137198604",
      "cover": "https://cdn-images.dzcdn.net/images/cover/7c8dcf39163d1ec4992686f4d2c848cb/500x500-000000-80-0-0.jpg",
      "deezerArtist": "Jason Donovan",
      "deezerTitle": "Sealed with a Kiss"
    }
  },
  {
    "rank": 41,
    "artist": "Tina Turner",
    "title": "The Best",
    "deezer": {
      "deezerID": 3167295,
      "deezerLink": "https://www.deezer.com/track/3167295",
      "cover": "https://cdn-images.dzcdn.net/images/cover/42024f50dc501575ae920ccf506fa4dd/500x500-000000-80-0-0.jpg",
      "deezerArtist": "Tina Turner",
      "deezerTitle": "The Best"
    }
  },
  {
    "rank": 42,
    "artist": "Black Box",
    "title": "Ride On Time",
    "deezer": {
      "deezerID": 70051871,
      "deezerLink": "https://www.deezer.com/track/70051871",
      "cover": "https://cdn-images.dzcdn.net/images/cover/ad31d939346f5770e86af0622c595d32/500x500-000000-80-0-0.jpg",
      "deezerArtist": "Black Box",
      "deezerTitle": "Ride on Time"
    }
  },
  {
    "rank": 43,
    "artist": "Louis Armstrong",
    "title": "What A Wonderful World",
    "deezer": {
      "deezerID": 13155119,
      "deezerLink": "https://www.deezer.com/track/13155119",
      "cover": "https://cdn-images.dzcdn.net/images/cover/f6b09cd325e2494e7b6c748d03e08736/500x500-000000-80-0-0.jpg",
      "deezerArtist": "Louis Armstrong",
      "deezerTitle": "What A Wonderful World"
    }
  },
  {
    "rank": 44,
    "artist": "Geoffrey Williams",
    "title": "Cinderella",
    "deezer": {
      "deezerID": 3601366,
      "deezerLink": "https://www.deezer.com/track/3601366",
      "cover": "https://cdn-images.dzcdn.net/images/cover/797a04745600965365cf96cc97e371c9/500x500-000000-80-0-0.jpg",
      "deezerArtist": "Geoffrey Williams",
      "deezerTitle": "Cinderella"
    }
  },
  {
    "rank": 45,
    "artist": "Roy Orbison",
    "title": "You Got It",
    "deezer": {
      "deezerID": 3570745,
      "deezerLink": "https://www.deezer.com/track/3570745",
      "cover": "https://cdn-images.dzcdn.net/images/cover/9ee5c23c852fbb882e895ee1dab46886/500x500-000000-80-0-0.jpg",
      "deezerArtist": "Roy Orbison",
      "deezerTitle": "You Got It"
    }
  },
  {
    "rank": 46,
    "artist": "Womack & Womack",
    "title": "Teardrops",
    "deezer": {
      "deezerID": 2516432551,
      "deezerLink": "https://www.deezer.com/track/2516432551",
      "cover": "https://cdn-images.dzcdn.net/images/cover/a926e646048f06c65e082e8fe53b9e8e/500x500-000000-80-0-0.jpg",
      "deezerArtist": "Womack & Womack",
      "deezerTitle": "Teardrops"
    }
  },
  {
    "rank": 47,
    "artist": "Queen",
    "title": "I Want It All",
    "deezer": {
      "deezerID": 15928225,
      "deezerLink": "https://www.deezer.com/track/15928225",
      "cover": "https://cdn-images.dzcdn.net/images/cover/52a6bc44b276e04b5889a1e2e741ba17/500x500-000000-80-0-0.jpg",
      "deezerArtist": "Queen",
      "deezerTitle": "I Want It All"
    }
  },
  {
    "rank": 48,
    "artist": "Soul II Soul",
    "title": "Keep On Movin'",
    "deezer": {
      "deezerID": 3125980,
      "deezerLink": "https://www.deezer.com/track/3125980",
      "cover": "https://cdn-images.dzcdn.net/images/cover/43edaf5a15623dff51ad07a617cbdf72/500x500-000000-80-0-0.jpg",
      "deezerArtist": "Soul II Soul",
      "deezerTitle": "Keep On Movin'"
    }
  },
  {
    "rank": 49,
    "artist": "Prince",
    "title": "Batdance",
    "deezer": {
      "deezerID": 3917698,
      "deezerLink": "https://www.deezer.com/track/3917698",
      "cover": "https://cdn-images.dzcdn.net/images/cover/7859ed5c0140a3afc304a2cbff2bee01/500x500-000000-80-0-0.jpg",
      "deezerArtist": "Prince",
      "deezerTitle": "Batdance"
    }
  },
  {
    "rank": 50,
    "artist": "The Christians, Holly Johnson, Paul McCartney, Gerry Marsden & Stock Aitken Waterman",
    "title": "Ferry 'Cross The Mersey"
  },
  {
    "rank": 51,
    "artist": "Mike Oldfield",
    "title": "Innocent",
    "deezer": {
      "deezerID": 3333198,
      "deezerLink": "https://www.deezer.com/track/3333198",
      "cover": "https://cdn-images.dzcdn.net/images/cover/e1ad9d687ce4c5ec8180dcb7be09c471/500x500-000000-80-0-0.jpg",
      "deezerArtist": "Mike Oldfield",
      "deezerTitle": "Innocent"
    }
  },
  {
    "rank": 52,
    "artist": "Pet Shop Boys",
    "title": "It's Alright",
    "deezer": {
      "deezerID": 3122980,
      "deezerLink": "https://www.deezer.com/track/3122980",
      "cover": "https://cdn-images.dzcdn.net/images/cover/5453ca81ae47f016b0aa7b55729da928/500x500-000000-80-0-0.jpg",
      "deezerArtist": "Pet Shop Boys",
      "deezerTitle": "It's Alright"
    }
  },
  {
    "rank": 53,
    "artist": "Bananarama / Lananeeneenoonoo",
    "title": "Help",
    "deezer": {
      "deezerID": 958533512,
      "deezerLink": "https://www.deezer.com/track/958533512",
      "cover": "https://cdn-images.dzcdn.net/images/cover/aadaaca792348e2711f429b71fc8c12d/500x500-000000-80-0-0.jpg",
      "deezerArtist": "Bananarama",
      "deezerTitle": "Help!"
    }
  },
  {
    "rank": 54,
    "artist": "Gladys Knight",
    "title": "Licence To Kill",
    "deezer": {
      "deezerID": 2434771,
      "deezerLink": "https://www.deezer.com/track/2434771",
      "cover": "https://cdn-images.dzcdn.net/images/cover/8e2f933d4277a5240b9c0b778dad8bf6/500x500-000000-80-0-0.jpg",
      "deezerArtist": "Gladys Knight",
      "deezerTitle": "Licence To Kill"
    }
  },
  {
    "rank": 55,
    "artist": "Fine Young Cannibals",
    "title": "Good Thing",
    "deezer": {
      "deezerID": 428850822,
      "deezerLink": "https://www.deezer.com/track/428850822",
      "cover": "https://cdn-images.dzcdn.net/images/cover/e6989e60c248d4aec0097212408e52eb/500x500-000000-80-0-0.jpg",
      "deezerArtist": "Fine Young Cannibals",
      "deezerTitle": "Good Thing"
    }
  },
  {
    "rank": 56,
    "artist": "Donna Summer",
    "title": "This Time I Know It's For Real",
    "deezer": {
      "deezerID": 81706450,
      "deezerLink": "https://www.deezer.com/track/81706450",
      "cover": "https://cdn-images.dzcdn.net/images/cover/b3a8fc8a361e41bd48e6d00822de4c62/500x500-000000-80-0-0.jpg",
      "deezerArtist": "Donna Summer",
      "deezerTitle": "This Time I Know It's for Real"
    }
  },
  {
    "rank": 57,
    "artist": "Michael Jackson",
    "title": "Smooth Criminal",
    "deezer": {
      "deezerID": 4603400,
      "deezerLink": "https://www.deezer.com/track/4603400",
      "cover": "https://cdn-images.dzcdn.net/images/cover/a0ad67d1beb761f2cb9f8b60e5bcf07a/500x500-000000-80-0-0.jpg",
      "deezerArtist": "Michael Jackson",
      "deezerTitle": "Smooth Criminal"
    }
  },
  {
    "rank": 58,
    "artist": "Hithouse",
    "title": "Jack To The Sound Of The Underground",
    "deezer": {
      "deezerID": 381908891,
      "deezerLink": "https://www.deezer.com/track/381908891",
      "cover": "https://cdn-images.dzcdn.net/images/cover/4c4f82a1cf006e47623c9ccd9cc34514/500x500-000000-80-0-0.jpg",
      "deezerArtist": "Hithouse",
      "deezerTitle": "Jack To The Sound Of The Underground"
    }
  },
  {
    "rank": 59,
    "artist": "The Jeremy Days",
    "title": "Brand New Toy",
    "deezer": {
      "deezerID": 571888272,
      "deezerLink": "https://www.deezer.com/track/571888272",
      "cover": "https://cdn-images.dzcdn.net/images/cover/9e90a814fafaae465da83ec7a54ee53f/500x500-000000-80-0-0.jpg",
      "deezerArtist": "The Jeremy Days",
      "deezerTitle": "Brand New Toy"
    }
  },
  {
    "rank": 60,
    "artist": "Kylie & Jason",
    "title": "Especially For You",
    "deezer": {
      "deezerID": 137197994,
      "deezerLink": "https://www.deezer.com/track/137197994",
      "cover": "https://cdn-images.dzcdn.net/images/cover/43ea55c5fc47601fcfe2295ce4617333/500x500-000000-80-0-0.jpg",
      "deezerArtist": "Kylie Minogue",
      "deezerTitle": "Especially for You"
    }
  },
  {
    "rank": 61,
    "artist": "Bee Gees",
    "title": "Ordinary Lives",
    "deezer": {
      "deezerID": 973613672,
      "deezerLink": "https://www.deezer.com/track/973613672",
      "cover": "https://cdn-images.dzcdn.net/images/cover/6eb00cbbca6464b97f700a08f53c4671/500x500-000000-80-0-0.jpg",
      "deezerArtist": "Bee Gees",
      "deezerTitle": "Ordinary Lives"
    }
  },
  {
    "rank": 62,
    "artist": "Kon Kan",
    "title": "I Beg Your Pardon",
    "deezer": {
      "deezerID": 85190994,
      "deezerLink": "https://www.deezer.com/track/85190994",
      "cover": "https://cdn-images.dzcdn.net/images/cover/c75ce63a50213709e8cd61625854a52e/500x500-000000-80-0-0.jpg",
      "deezerArtist": "Kon Kan",
      "deezerTitle": "I Beg Your Pardon (I Never Promised You a Rose Garden)"
    }
  },
  {
    "rank": 63,
    "artist": "Milli Vanilli",
    "title": "Baby Don't Forget My Number",
    "deezer": {
      "deezerID": 2463954415,
      "deezerLink": "https://www.deezer.com/track/2463954415",
      "cover": "https://cdn-images.dzcdn.net/images/cover/93438b5905da18db776bad2b7fa0e630/500x500-000000-80-0-0.jpg",
      "deezerArtist": "Milli Vanilli",
      "deezerTitle": "Baby Don't Forget My Number"
    }
  },
  {
    "rank": 64,
    "artist": "Phil Collins",
    "title": "A Groovy Kind Of Love",
    "deezer": {
      "deezerID": 134036244,
      "deezerLink": "https://www.deezer.com/track/134036244",
      "cover": "https://cdn-images.dzcdn.net/images/cover/73e6481676a8ab3e93f0f7b79a9cff68/500x500-000000-80-0-0.jpg",
      "deezerArtist": "Phil Collins",
      "deezerTitle": "A Groovy Kind of Love"
    }
  },
  {
    "rank": 65,
    "artist": "Sandra",
    "title": "We'll Be Together",
    "deezer": {
      "deezerID": 3283096,
      "deezerLink": "https://www.deezer.com/track/3283096",
      "cover": "https://cdn-images.dzcdn.net/images/cover/89b881a0be3baa84ca148abc4ebd7177/500x500-000000-80-0-0.jpg",
      "deezerArtist": "Sandra",
      "deezerTitle": "We'll Be Together"
    }
  },
  {
    "rank": 66,
    "artist": "Tone Loc",
    "title": "Wild Thing"
  },
  {
    "rank": 67,
    "artist": "Hanne Haller",
    "title": "Mein lieber Mann",
    "deezer": {
      "deezerID": 2322553,
      "deezerLink": "https://www.deezer.com/track/2322553",
      "cover": "https://cdn-images.dzcdn.net/images/cover/7bffb6369163185e499c84a9bb672efe/500x500-000000-80-0-0.jpg",
      "deezerArtist": "Hanne Haller",
      "deezerTitle": "Mein lieber Mann"
    }
  },
  {
    "rank": 68,
    "artist": "Rick Astley",
    "title": "Take Me To Your Heart",
    "deezer": {
      "deezerID": 781592682,
      "deezerLink": "https://www.deezer.com/track/781592682",
      "cover": "https://cdn-images.dzcdn.net/images/cover/fe779e632872f7c6e9f1c84ffa7afc33/500x500-000000-80-0-0.jpg",
      "deezerArtist": "Rick Astley",
      "deezerTitle": "Take Me To Your Heart"
    }
  },
  {
    "rank": 69,
    "artist": "The Art Of Noise feat. Tom Jones",
    "title": "Kiss",
    "deezer": {
      "deezerID": 732907,
      "deezerLink": "https://www.deezer.com/track/732907",
      "cover": "https://cdn-images.dzcdn.net/images/cover/990aee4b92db6e7a65244319108654aa/500x500-000000-80-0-0.jpg",
      "deezerArtist": "Art of Noise",
      "deezerTitle": "Kiss (feat. Tom Jones)"
    }
  },
  {
    "rank": 70,
    "artist": "Jason Donovan",
    "title": "Too Many Broken Hearts",
    "deezer": {
      "deezerID": 137232490,
      "deezerLink": "https://www.deezer.com/track/137232490",
      "cover": "https://cdn-images.dzcdn.net/images/cover/8cfe045b887ec5f69552a362924f8bfa/500x500-000000-80-0-0.jpg",
      "deezerArtist": "Jason Donovan",
      "deezerTitle": "Too Many Broken Hearts"
    }
  },
  {
    "rank": 71,
    "artist": "Rufus & Chaka Khan",
    "title": "Ain't Nobody (Remix)",
    "deezer": {
      "deezerID": 4094693,
      "deezerLink": "https://www.deezer.com/track/4094693",
      "cover": "https://cdn-images.dzcdn.net/images/cover/f7b06fcbb73e5b123fad6bcfabb043ed/500x500-000000-80-0-0.jpg",
      "deezerArtist": "Rufus",
      "deezerTitle": "Ain't Nobody"
    }
  },
  {
    "rank": 72,
    "artist": "Robin Beck",
    "title": "Save Up All Your Tears"
  },
  {
    "rank": 73,
    "artist": "Martika",
    "title": "Toy Soldiers",
    "deezer": {
      "deezerID": 899944,
      "deezerLink": "https://www.deezer.com/track/899944",
      "cover": "https://cdn-images.dzcdn.net/images/cover/6102aef6106820dc03d523459910503a/500x500-000000-80-0-0.jpg",
      "deezerArtist": "Martika",
      "deezerTitle": "Toy Soldiers"
    }
  },
  {
    "rank": 74,
    "artist": "Jürgen Drews",
    "title": "Irgendwann, irgendwo, irgendwie (seh'n wir uns wieder)",
    "deezer": {
      "deezerID": 1103918582,
      "deezerLink": "https://www.deezer.com/track/1103918582",
      "cover": "https://cdn-images.dzcdn.net/images/cover/684ca41967599827803fcc016d885730/500x500-000000-80-0-0.jpg",
      "deezerArtist": "Jürgen Drews",
      "deezerTitle": "Irgendwann irgendwo irgendwie"
    }
  },
  {
    "rank": 75,
    "artist": "Wee Papa Girl Rappers",
    "title": "Wee Rule",
    "deezer": {
      "deezerID": 133518250,
      "deezerLink": "https://www.deezer.com/track/133518250",
      "cover": "https://cdn-images.dzcdn.net/images/cover/2a40824154c3ad3b9543d92d8dcbc78f/500x500-000000-80-0-0.jpg",
      "deezerArtist": "Wee Papa Girl Rappers",
      "deezerTitle": "Wee Rule"
    }
  },
  {
    "rank": 76,
    "artist": "Depeche Mode",
    "title": "Personal Jesus",
    "deezer": {
      "deezerID": 68513563,
      "deezerLink": "https://www.deezer.com/track/68513563",
      "cover": "https://cdn-images.dzcdn.net/images/cover/55972109f7c4049deb78402a94ee3b7b/500x500-000000-80-0-0.jpg",
      "deezerArtist": "Depeche Mode",
      "deezerTitle": "Personal Jesus"
    }
  },
  {
    "rank": 77,
    "artist": "Original Naabtal Duo",
    "title": "Patrona Bavariae",
    "deezer": {
      "deezerID": 3318525,
      "deezerLink": "https://www.deezer.com/track/3318525",
      "cover": "https://cdn-images.dzcdn.net/images/cover/40c63217628dc63a4cdb9a061a8ac231/500x500-000000-80-0-0.jpg",
      "deezerArtist": "Original Naabtal Duo",
      "deezerTitle": "Patrona Bavariae"
    }
  },
  {
    "rank": 78,
    "artist": "Klaus & Klaus",
    "title": "Der Eiermann",
    "deezer": {
      "deezerID": 481857302,
      "deezerLink": "https://www.deezer.com/track/481857302",
      "cover": "https://cdn-images.dzcdn.net/images/cover/94b165e7bde8adea95696c588b203ad1/500x500-000000-80-0-0.jpg",
      "deezerArtist": "Klaus & Klaus",
      "deezerTitle": "Der Eiermann"
    }
  },
  {
    "rank": 79,
    "artist": "Pet Shop Boys",
    "title": "Left To My Own Devices",
    "deezer": {
      "deezerID": 3122979,
      "deezerLink": "https://www.deezer.com/track/3122979",
      "cover": "https://cdn-images.dzcdn.net/images/cover/5453ca81ae47f016b0aa7b55729da928/500x500-000000-80-0-0.jpg",
      "deezerArtist": "Pet Shop Boys",
      "deezerTitle": "Left to My Own Devices"
    }
  },
  {
    "rank": 80,
    "artist": "Bobby Brown",
    "title": "My Prerogative",
    "deezer": {
      "deezerID": 921945582,
      "deezerLink": "https://www.deezer.com/track/921945582",
      "cover": "https://cdn-images.dzcdn.net/images/cover/d59ea3d4045200b81567669146b62d7d/500x500-000000-80-0-0.jpg",
      "deezerArtist": "Bobby Brown",
      "deezerTitle": "My Prerogative"
    }
  },
  {
    "rank": 81,
    "artist": "Honesty 69",
    "title": "French Kiss",
    "deezer": {
      "deezerID": 15464206,
      "deezerLink": "https://www.deezer.com/track/15464206",
      "cover": "https://cdn-images.dzcdn.net/images/cover/5234d0d0f22b1cf133b8525fd3ef3f16/500x500-000000-80-0-0.jpg",
      "deezerArtist": "Honesty 69",
      "deezerTitle": "French Kiss"
    }
  },
  {
    "rank": 82,
    "artist": "Sandra",
    "title": "Around My Heart",
    "deezer": {
      "deezerID": 125541454,
      "deezerLink": "https://www.deezer.com/track/125541454",
      "cover": "https://cdn-images.dzcdn.net/images/cover/343361545e65ba4178d4146a9f107333/500x500-000000-80-0-0.jpg",
      "deezerArtist": "Sandra",
      "deezerTitle": "Around My Heart"
    }
  },
  {
    "rank": 83,
    "artist": "Petula Clark",
    "title": "Downtown '88",
    "deezer": {
      "deezerID": 143038368,
      "deezerLink": "https://www.deezer.com/track/143038368",
      "cover": "https://cdn-images.dzcdn.net/images/cover/c7faa57b45f741fe69cd2ed1424bebd5/500x500-000000-80-0-0.jpg",
      "deezerArtist": "Petula Clark",
      "deezerTitle": "Downtown '88"
    }
  },
  {
    "rank": 84,
    "artist": "David Hasselhoff",
    "title": "Is Everybody Happy",
    "deezer": {
      "deezerID": 122469872,
      "deezerLink": "https://www.deezer.com/track/122469872",
      "cover": "https://cdn-images.dzcdn.net/images/cover/d8bc7032d3407e43b8cf4c4578ab12c0/500x500-000000-80-0-0.jpg",
      "deezerArtist": "David Hasselhoff",
      "deezerTitle": "Is Everybody Happy"
    }
  },
  {
    "rank": 85,
    "artist": "Jermaine Stewart",
    "title": "Don't Talk Dirty To Me",
    "deezer": {
      "deezerID": 1379139942,
      "deezerLink": "https://www.deezer.com/track/1379139942",
      "cover": "https://cdn-images.dzcdn.net/images/cover/bdcd95e851a76e8389ae75f8658a9e57/500x500-000000-80-0-0.jpg",
      "deezerArtist": "Jermaine Stewart",
      "deezerTitle": "Don't Talk Dirty To Me"
    }
  },
  {
    "rank": 86,
    "artist": "Simply Red",
    "title": "It's Only Love",
    "deezer": {
      "deezerID": 75814710,
      "deezerLink": "https://www.deezer.com/track/75814710",
      "cover": "https://cdn-images.dzcdn.net/images/cover/6082ea7f45ec9a7093225b85bd6ebadd/500x500-000000-80-0-0.jpg",
      "deezerArtist": "Simply Red",
      "deezerTitle": "It's Only Love"
    }
  },
  {
    "rank": 87,
    "artist": "De La Soul",
    "title": "Me Myself And I",
    "deezer": {
      "deezerID": 2048503687,
      "deezerLink": "https://www.deezer.com/track/2048503687",
      "cover": "https://cdn-images.dzcdn.net/images/cover/e44ecd488594e49fb3ac99023d0078d5/500x500-000000-80-0-0.jpg",
      "deezerArtist": "De La Soul",
      "deezerTitle": "Me Myself and I"
    }
  },
  {
    "rank": 88,
    "artist": "Simply Red",
    "title": "If You Don't Know Me By Now",
    "deezer": {
      "deezerID": 2477046,
      "deezerLink": "https://www.deezer.com/track/2477046",
      "cover": "https://cdn-images.dzcdn.net/images/cover/a54a3f7dca98a52cbaaeed00ae2e3937/500x500-000000-80-0-0.jpg",
      "deezerArtist": "Simply Red",
      "deezerTitle": "If You Don't Know Me by Now"
    }
  },
  {
    "rank": 89,
    "artist": "Depeche Mode",
    "title": "Everything Counts (Live)",
    "deezer": {
      "deezerID": 68513660,
      "deezerLink": "https://www.deezer.com/track/68513660",
      "cover": "https://cdn-images.dzcdn.net/images/cover/55972109f7c4049deb78402a94ee3b7b/500x500-000000-80-0-0.jpg",
      "deezerArtist": "Depeche Mode",
      "deezerTitle": "Everything Counts"
    }
  },
  {
    "rank": 90,
    "artist": "Nino de Angelo",
    "title": "Samuraj",
    "deezer": {
      "deezerID": 357126931,
      "deezerLink": "https://www.deezer.com/track/357126931",
      "cover": "https://cdn-images.dzcdn.net/images/cover/dd1cee841bf2c8ffe4cab67d9e851bef/500x500-000000-80-0-0.jpg",
      "deezerArtist": "Nino De Angelo",
      "deezerTitle": "Samuraj"
    }
  },
  {
    "rank": 91,
    "artist": "Yazz",
    "title": "Stand Up For Your Love Rights",
    "deezer": {
      "deezerID": 107758348,
      "deezerLink": "https://www.deezer.com/track/107758348",
      "cover": "https://cdn-images.dzcdn.net/images/cover/40fb90c0eaeeddfe26993da91844e094/500x500-000000-80-0-0.jpg",
      "deezerArtist": "Yazz",
      "deezerTitle": "Stand Up For Your Love Rights"
    }
  },
  {
    "rank": 92,
    "artist": "Kylie Minogue",
    "title": "Hand On Your Heart",
    "deezer": {
      "deezerID": 137232358,
      "deezerLink": "https://www.deezer.com/track/137232358",
      "cover": "https://cdn-images.dzcdn.net/images/cover/a4329d5d528ceda7b2e9c73080b69557/500x500-000000-80-0-0.jpg",
      "deezerArtist": "Kylie Minogue",
      "deezerTitle": "Hand on Your Heart"
    }
  },
  {
    "rank": 93,
    "artist": "Bad Boys Blue",
    "title": "Lady In Black",
    "deezer": {
      "deezerID": 15792096,
      "deezerLink": "https://www.deezer.com/track/15792096",
      "cover": "https://cdn-images.dzcdn.net/images/cover/5537c023f59757e0c75a0da7e54426df/500x500-000000-80-0-0.jpg",
      "deezerArtist": "Bad Boys Blue",
      "deezerTitle": "Lady In Black"
    }
  },
  {
    "rank": 94,
    "artist": "Texas",
    "title": "I Don't Want A Lover",
    "deezer": {
      "deezerID": 2099242707,
      "deezerLink": "https://www.deezer.com/track/2099242707",
      "cover": "https://cdn-images.dzcdn.net/images/cover/08d063773367544b5b372c08d33f367e/500x500-000000-80-0-0.jpg",
      "deezerArtist": "Texas",
      "deezerTitle": "I Don't Want a Lover"
    }
  },
  {
    "rank": 95,
    "artist": "Chris Thompson",
    "title": "The Challenge (Face It)",
    "deezer": {
      "deezerID": 94796562,
      "deezerLink": "https://www.deezer.com/track/94796562",
      "cover": "https://cdn-images.dzcdn.net/images/cover/ab507f7e0ba96df2fef30d6aebef6e9f/500x500-000000-80-0-0.jpg",
      "deezerArtist": "Chris Thompson",
      "deezerTitle": "The Challenge"
    }
  },
  {
    "rank": 96,
    "artist": "Erasure",
    "title": "Crackers International"
  },
  {
    "rank": 97,
    "artist": "Stephan Remmler",
    "title": "Keine Angst hat der Papa mir gesagt (Keine Angst hat die Mama mir gesagt)",
    "deezer": {
      "deezerID": 2504717,
      "deezerLink": "https://www.deezer.com/track/2504717",
      "cover": "https://cdn-images.dzcdn.net/images/cover/b3a7513135bdb2774555fa91ddc8ae9b/500x500-000000-80-0-0.jpg",
      "deezerArtist": "Stephan Remmler",
      "deezerTitle": "Keine Angst Hat Der Papa Mir Gesagt (Mama)"
    }
  },
  {
    "rank": 98,
    "artist": "Die Ärzte",
    "title": "Bitte bitte",
    "deezer": {
      "deezerID": 1095340182,
      "deezerLink": "https://www.deezer.com/track/1095340182",
      "cover": "https://cdn-images.dzcdn.net/images/cover/a43c4d893bfa5e62db38a91ac0f38542/500x500-000000-80-0-0.jpg",
      "deezerArtist": "Die Ärzte",
      "deezerTitle": "Bitte, Bitte"
    }
  },
  {
    "rank": 99,
    "artist": "Inner City",
    "title": "Ain't Nobody Better",
    "deezer": {
      "deezerID": 3133680,
      "deezerLink": "https://www.deezer.com/track/3133680",
      "cover": "https://cdn-images.dzcdn.net/images/cover/1f99d88dcc3a088d660ecb9a4d8bf766/500x500-000000-80-0-0.jpg",
      "deezerArtist": "Inner City",
      "deezerTitle": "Ain't Nobody Better"
    }
  },
  {
    "rank": 100,
    "artist": "Ten City",
    "title": "That's The Way Love Is",
    "deezer": {
      "deezerID": 2813255,
      "deezerLink": "https://www.deezer.com/track/2813255",
      "cover": "https://cdn-images.dzcdn.net/images/cover/95df7ee7f3008e193940c238998f1c25/500x500-000000-80-0-0.jpg",
      "deezerArtist": "Ten City",
      "deezerTitle": "That's The Way Love Is"
    }
  }
]